cerbose/__init__.py
cerbose-1.0.1.post1.dist-info/licenses/LICENSE
cerbose-1.0.1.post1.dist-info/licenses/LICENSE-GPL
cerbose-1.0.1.post1.dist-info/licenses/LICENSE-LGPL
cerbose-1.0.1.post1.dist-info/licenses/LICENSE-MIT
cerbose-1.0.1.post1.dist-info/METADATA
cerbose-1.0.1.post1.dist-info/WHEEL
cerbose-1.0.1.post1.dist-info/top_level.txt
cerbose-1.0.1.post1.dist-info/RECORD
