Metadata-Version: 2.4
Name: cerbose
Version: 1.0.1.post1
Summary: A simple Python library for making colourful, tagged terminal output, along with additional console features.
Author: jasperredis
License: LGPL-3.0-or-later
Project-URL: Homepage, https://jasperredis.github.io/cerbose
Project-URL: Docs, https://jasperredis.github.io/cerbose/docs.html
Project-URL: Repository, https://github.com/jasperredis/cerbose
Project-URL: PyPI, https://pypi.org/project/cerbose/
Project-URL: jasperredis, https://jris.straw.page
Keywords: terminal,colors,progress bar,console
Requires-Python: >=3.7
License-File: LICENSE
License-File: LICENSE-GPL
License-File: LICENSE-LGPL
License-File: LICENSE-MIT
Requires-Dist: colorama>=0.4.6
Dynamic: license-file
